cellpylib3d/__init__.py
cellpylib3d/ca_functions3d.py
cellpylib3d/ca_functionsParallel.py
cellpylib3d/ca_rules.py
cellpylib3d-1.0.2.dist-info/METADATA
cellpylib3d-1.0.2.dist-info/WHEEL
cellpylib3d-1.0.2.dist-info/licenses/LICENSE
cellpylib3d-1.0.2.dist-info/RECORD
