Metadata-Version: 2.1
Name: cellpylib3d
Version: 1.0.2
Summary: An extension of CellPyLib, enabling 3d cellular automaton. 
Project-URL: Homepage, https://github.com/Cutwell/cellpylib-3d
Project-URL: Bug Tracker, https://github.com/Cutwell/cellpylib-3d/issues
Author-email: "Z. Smith" <zachsmith.dev@gmail.com>
License: 
Classifier: License :: OSI Approved :: Apache Software License
Classifier: Operating System :: OS Independent
Classifier: Programming Language :: Python :: 3.7
Requires-Python: >=3.7
